HiWorld/HiWorld.py
HiWorld/__init__.py
Hey_World-0.0.8.dist-info/LICENSE
Hey_World-0.0.8.dist-info/METADATA
Hey_World-0.0.8.dist-info/WHEEL
Hey_World-0.0.8.dist-info/top_level.txt
Hey_World-0.0.8.dist-info/RECORD
